{
    "titre": "Jardinière grimpante.",
    "main_image_url": "https://wikifab.org/images/thumb/b/b1/Jardini_re_grimpante._montage_avec_plante_impresssion.png/ia-baf152e1fb06ce4c824b0e3d06cae63b-px-Jardini_re_grimpante._montage_avec_plante_impresssion.png.png",
    "main_image_caption": "Jardnière empilable rattachée à une branche d'arbre par une corde-tuteur.",
    "difficulte": "Easy Facile",
    "duree": "5 hour(s) heure(s)",
    "cout": "30 EUR (€)",
    "source_link": "https://wikifab.org/wiki/Jardinière_grimpante.",
    "intro": "Ce tutoriel explique comment jardinière grimpante..",
    "intro_items": [],
    "materiaux": [
        "Plaque de plastique recyclé, corde de 10mm de diamètre et 2m de long, jardinière de récupération, tasseau de bois, rivets."
    ],
    "outils": [
        "<ul><li>Perceuse, dremel, cutter.</li></ul>"
    ],
    "etapes": [
        {
            "html": "<strong>1. Étape 1 - I- Découper les planches.</strong><div class='step-images count-3'><figure><img src='https://wikifab.org/images/thumb/e/ee/Cloison_grimpante._20250507_124514.jpg/800px-Cloison_grimpante._20250507_124514.jpg' alt='Cloison grimpante. 20250507 124514.jpg' loading='lazy'></figure><figure><img src='https://wikifab.org/images/thumb/f/fb/Cloison_grimpante._IMG_4109_1_-4_page-0001.jpg/800px-Cloison_grimpante._IMG_4109_1_-4_page-0001.jpg' alt='Cloison grimpante. IMG 4109 1 -4 page-0001.jpg' loading='lazy'></figure><figure><img src='https://wikifab.org/images/thumb/9/92/Cloison_grimpante._IMG_4109_1_-3_page-0001.jpg/800px-Cloison_grimpante._IMG_4109_1_-3_page-0001.jpg' alt='Cloison grimpante. IMG 4109 1 -3 page-0001.jpg' loading='lazy'></figure></div><p><strong>Étapes :</strong></p><ol><li>-Coupez des plaques de plastique recyclé en fonction de la taille de votre jardinière et ajouter 10 centimètres de chaque côté à l'horizontal.</li><li>-Tracez et découpez des motifs à l’aide d’une dremel dans ce qui dépasse.</li></ol>",
            "fichiers": [
                {
                    "nom": "",
                    "type": "",
                    "description": "",
                    "lien": ""
                }
            ]
        },
        {
            "html": "<strong>2. Étape 2 - II- Trouer la jardinière.</strong><div class='step-images count-2'><figure><img src='https://wikifab.org/images/thumb/0/06/Jardini_re_grimpante._20250507_132138.jpg/800px-Jardini_re_grimpante._20250507_132138.jpg' alt='Jardini re grimpante. 20250507 132138.jpg' loading='lazy'></figure><figure><img src='https://wikifab.org/images/thumb/b/b8/Cloison_grimpante._20250507_132539.jpg/800px-Cloison_grimpante._20250507_132539.jpg' alt='Cloison grimpante. 20250507 132539.jpg' loading='lazy'></figure></div><p><strong>Étapes :</strong></p><ol><li>-Créez un trou de la même taille que votre tasseau pour pouvoir le faire glisser dans le fond de votre jardinière.</li></ol>",
            "fichiers": [
                {
                    "nom": "",
                    "type": "",
                    "description": "",
                    "lien": ""
                }
            ]
        },
        {
            "html": "<strong>3. Étape 3 - III- Accrochez les planches aux jardinières.</strong><div class='step-images count-3'><figure><img src='https://wikifab.org/images/thumb/7/7b/Jardini_re_grimpante._20250507_134342.jpg/800px-Jardini_re_grimpante._20250507_134342.jpg' alt='Jardini re grimpante. 20250507 134342.jpg' loading='lazy'></figure><figure><img src='https://wikifab.org/images/thumb/0/0d/Jardini_re_grimpante._20250507_134356.jpg/800px-Jardini_re_grimpante._20250507_134356.jpg' alt='Jardini re grimpante. 20250507 134356.jpg' loading='lazy'></figure><figure><img src='https://wikifab.org/images/thumb/f/fe/Jardini_re_grimpante._20250507_134402.jpg/800px-Jardini_re_grimpante._20250507_134402.jpg' alt='Jardini re grimpante. 20250507 134402.jpg' loading='lazy'></figure></div><p><strong>Étapes :</strong></p><ol><li>-Percez la planche et la jardinière à l’aide d’une perceuse.</li><li>-Fixez vos planches sur les deux côtés de votre jardinière. Ici nous avons utilisés des rivets et une riveteuse à main.</li></ol>",
            "fichiers": [
                {
                    "nom": "",
                    "type": "",
                    "description": "",
                    "lien": ""
                }
            ]
        },
        {
            "html": "<strong>4. Étape 4 - IV- Assemblage.</strong><div class='step-images count-3'><figure><img src='https://wikifab.org/images/thumb/2/24/Jardini_re_grimpante._20250507_142447.jpg/800px-Jardini_re_grimpante._20250507_142447.jpg' alt='Jardini re grimpante. 20250507 142447.jpg' loading='lazy'></figure><figure><img src='https://wikifab.org/images/thumb/2/20/Jardini_re_grimpante._IMG_4109_1_-1_page-0001.jpg/800px-Jardini_re_grimpante._IMG_4109_1_-1_page-0001.jpg' alt='Jardini re grimpante. IMG 4109 1 -1 page-0001.jpg' loading='lazy'></figure><figure><img src='https://wikifab.org/images/thumb/6/60/Jardini_re_grimpante._IMG_4109_1_-2_page-0001.jpg/800px-Jardini_re_grimpante._IMG_4109_1_-2_page-0001.jpg' alt='Jardini re grimpante. IMG 4109 1 -2 page-0001.jpg' loading='lazy'></figure></div><p><strong>Étapes :</strong></p><ol><li>-Faire glisser les jardinières sur le tasseau, adapter leur nombre en fonction de la hauteur souhaitée.</li></ol>",
            "fichiers": [
                {
                    "nom": "",
                    "type": "",
                    "description": "",
                    "lien": ""
                }
            ]
        },
        {
            "html": "<strong>5. Étape 5 - V- Préparer le matériel pour le tuteur.</strong><div class='step-images count-3'><figure><img src='https://wikifab.org/images/thumb/c/c4/Jardini_re_grimpante._IMG_4131.jpeg/800px-Jardini_re_grimpante._IMG_4131.jpeg' alt='Jardini re grimpante. IMG 4131.jpeg' loading='lazy'></figure><figure><img src='https://wikifab.org/images/d/da/Jardini_re_grimpante._IMG_4132.jpeg' alt='Jardini re grimpante. IMG 4132.jpeg' loading='lazy'></figure><figure><img src='https://wikifab.org/images/4/42/Jardini_re_grimpante._IMG_4128.jpeg' alt='Jardini re grimpante. IMG 4128.jpeg' loading='lazy'></figure></div><p><strong>Étapes :</strong></p><ol><li>-Découpez des morceaux de la plaque de PP en forme de losange aléatoires. Ici de taille d’environ 10 centimètres.</li><li>-Percez l’extrémité à l’aide d’une perceuse.</li><li>-Séparez une corde afin d’atteindre un diamètre qui peut passer dans le trou fait précédemment.</li></ol>",
            "fichiers": [
                {
                    "nom": "",
                    "type": "",
                    "description": "",
                    "lien": ""
                }
            ]
        },
        {
            "html": "<strong>6. Étape 6 - VI- Assembler le tuteur.</strong><div class='step-images count-4'><figure><img src='https://wikifab.org/images/thumb/6/66/Jardini_re_grimpante._IMG_4134.jpeg/800px-Jardini_re_grimpante._IMG_4134.jpeg' alt='Jardini re grimpante. IMG 4134.jpeg' loading='lazy'></figure><figure><img src='https://wikifab.org/images/thumb/b/b6/Jardini_re_grimpante._IMG_4133.jpeg/800px-Jardini_re_grimpante._IMG_4133.jpeg' alt='Jardini re grimpante. IMG 4133.jpeg' loading='lazy'></figure><figure><img src='https://wikifab.org/images/thumb/9/9c/Jardini_re_grimpante._IMG_4137.jpeg/800px-Jardini_re_grimpante._IMG_4137.jpeg' alt='Jardini re grimpante. IMG 4137.jpeg' loading='lazy'></figure><figure><img src='https://wikifab.org/images/thumb/2/25/Jardini_re_grimpante._IMG_4139.jpeg/800px-Jardini_re_grimpante._IMG_4139.jpeg' alt='Jardini re grimpante. IMG 4139.jpeg' loading='lazy'></figure></div><p><strong>Étapes :</strong></p><ol><li>-Passez la corde une première fois dans le trou.</li><li>-Puis faire une boucle et la passer une deuxième fois.</li><li>-Serrez la corde.</li><li>-Répétez le processus tous les 20 centimètres et sur autant de cordes que nécessaire.</li></ol>",
            "fichiers": [
                {
                    "nom": "",
                    "type": "",
                    "description": "",
                    "lien": ""
                }
            ]
        },
        {
            "html": "<strong>7. Étape 7 - VII- Assembler les éléments.</strong><div class='step-images count-2'><figure><img src='https://wikifab.org/images/thumb/5/58/Jardini_re_grimpante._IMG_1880.jpg/800px-Jardini_re_grimpante._IMG_1880.jpg' alt='Jardini re grimpante. IMG 1880.jpg' loading='lazy'></figure><figure><img src='https://wikifab.org/images/thumb/d/dd/Jardini_re_grimpante._IMG_1884_2.jpg/800px-Jardini_re_grimpante._IMG_1884_2.jpg' alt='Jardini re grimpante. IMG 1884 2.jpg' loading='lazy'></figure></div><p><strong>Étapes :</strong></p><ol><li>-Accrochez les cordes-tuteur aux jardinières sur la partie trouée.</li><li>-Fixez la corde à une branche d'arbre en hauteur.</li><li>-Plantez du jasmin étoilé et laissez le grimper et créer une cloison parfumée et naturelle.<ul><li>Erreur lors de la création de la miniature : Fichier avec des dimensions supérieures à 12,5 MP</li></ul></li></ol>",
            "fichiers": [
                {
                    "nom": "",
                    "type": "",
                    "description": "",
                    "lien": ""
                }
            ]
        }
    ],
    "remarques": "",
    "mentions_legales": []
}