{
    "Chauferette DIY": {
        "titre": [
            "Chauferette DIY"
        ],
        "image": [
            {
                "url": "https://wiki.lowtechlab.org/images/thumb/6/6b/Chauferette_DIY_0.png/ia-671d43a72627f9e13805502b833a2cb8-px-Chauferette_DIY_0.png.png",
                "alt": "",
                "description": "Chaufferette mains"
            }
        ],
        "difficulté": [
            "Easy Facile"
        ],
        "durée": [
            "1,5 hour(s) heure(s)"
        ],
        "coût": [
            "1 EUR (€)"
        ],
        "liens": [
            "https://wiki.lowtechlab.org/wiki/Chauferette_DIY"
        ],
        "introduction": [],
        "mentions légales": [],
        "matériaux": [
            {
                "titre": "- 500 ml Vinaigre blanc",
                "sous_items": []
            },
            {
                "titre": "- 35g Bicarbonate de soude",
                "sous_items": []
            },
            {
                "titre": "-500 ml Eau bouillante",
                "sous_items": []
            }
        ],
        "outils": [
            {
                "titre": "",
                "sous_items": [
                    "-Filtre à café",
                    "-Cuillère",
                    "-Casserole",
                    "-Sachet",
                    "-Entonnoir",
                    "-Trombone"
                ]
            }
        ],
        "étapes": [
            {
                "numero": 1,
                "titre": "Étape 1 -",
                "solutions": [
                    {
                        "objectif": "",
                        "materiaux_outils": [],
                        "etapes": [
                            {
                                "titre": "Mettre 500mL de vinaigre dans un récipient et ajouter doucement le bicarbonate de soude (Vous pourrez observer un dégagement gazeux par formation de mousse, c'est du dioxyde de carbone).",
                                "sous_etapes": []
                            }
                        ],
                        "remarques": [],
                        "fichiers": [
                            {
                                "nom": "",
                                "type": "",
                                "description": "",
                                "lien": ""
                            }
                        ],
                        "images": []
                    }
                ]
            },
            {
                "numero": 2,
                "titre": "Étape 2 -",
                "solutions": [
                    {
                        "objectif": "",
                        "materiaux_outils": [],
                        "etapes": [
                            {
                                "titre": "Verser cette solution dans les 500mL d'eau bouillante dans la casserole et laisser évaporer la solution: on remarque alors la formation de cristaux au fond de la casserole.",
                                "sous_etapes": []
                            }
                        ],
                        "remarques": [],
                        "fichiers": [
                            {
                                "nom": "",
                                "type": "",
                                "description": "",
                                "lien": ""
                            }
                        ],
                        "images": []
                    }
                ]
            },
            {
                "numero": 3,
                "titre": "Étape 3 -",
                "solutions": [
                    {
                        "objectif": "",
                        "materiaux_outils": [],
                        "etapes": [
                            {
                                "titre": "Retirer les cristaux au fond de la casserole et les broyer afin de les rentrer dans le contenant ( ici gourde pompotes).",
                                "sous_etapes": []
                            }
                        ],
                        "remarques": [],
                        "fichiers": [
                            {
                                "nom": "",
                                "type": "",
                                "description": "",
                                "lien": ""
                            }
                        ],
                        "images": []
                    }
                ]
            },
            {
                "numero": 4,
                "titre": "Étape 4 -",
                "solutions": [
                    {
                        "objectif": "",
                        "materiaux_outils": [],
                        "etapes": [
                            {
                                "titre": "Faire bouillir de l'eau et laisser fondre le mélange dans la gourde à basse température jusqu'à ce que le mélange soit liquide.",
                                "sous_etapes": []
                            }
                        ],
                        "remarques": [],
                        "fichiers": [
                            {
                                "nom": "",
                                "type": "",
                                "description": "",
                                "lien": ""
                            }
                        ],
                        "images": []
                    }
                ]
            },
            {
                "numero": 5,
                "titre": "Étape 5 -",
                "solutions": [
                    {
                        "objectif": "",
                        "materiaux_outils": [],
                        "etapes": [
                            {
                                "titre": "Laisser le sachet reposer à l'air libre en évitant tout choc.",
                                "sous_etapes": []
                            }
                        ],
                        "remarques": [],
                        "fichiers": [
                            {
                                "nom": "",
                                "type": "",
                                "description": "",
                                "lien": ""
                            }
                        ],
                        "images": []
                    }
                ]
            },
            {
                "numero": 6,
                "titre": "Étape 6 -",
                "solutions": [
                    {
                        "objectif": "",
                        "materiaux_outils": [],
                        "etapes": [
                            {
                                "titre": "Ajouter le trombone et malaxer par la suite le sachet, pour entraîner la cristallisation d'acétate de sodium qui, étant exothermique, va nous fournir de la chaleur !",
                                "sous_etapes": []
                            }
                        ],
                        "remarques": [],
                        "fichiers": [
                            {
                                "nom": "",
                                "type": "",
                                "description": "",
                                "lien": ""
                            }
                        ],
                        "images": []
                    }
                ]
            },
            {
                "numero": 7,
                "titre": "Étape 7 -",
                "solutions": [
                    {
                        "objectif": "",
                        "materiaux_outils": [],
                        "etapes": [
                            {
                                "titre": "Afin de la réutiliser, répéter l'etape 4 et 5.",
                                "sous_etapes": []
                            }
                        ],
                        "remarques": [],
                        "fichiers": [
                            {
                                "nom": "",
                                "type": "",
                                "description": "",
                                "lien": ""
                            }
                        ],
                        "images": []
                    }
                ]
            }
        ],
        "annexes": []
    }
}